test2/__init__.py
test2/generate_refactoring.py
test2/processing_source_code.py
test2/setup.py
test2/textaugment.py
test2/util.py
test3/1.py
test3/__init__.py
test3/demo.py
test3/generate_refactoring.py
test3/main.py
test3/processing_source_code.py
test3/refactoring_methods.py
test3/setup.py
test3/test.py
test3/textaugment.py
test3/util.py
zwj_Pypi/__init__.py
zwj_Pypi/main.py
zwj_Pypi-0.1.dist-info/METADATA
zwj_Pypi-0.1.dist-info/WHEEL
zwj_Pypi-0.1.dist-info/top_level.txt
zwj_Pypi-0.1.dist-info/RECORD
