Metadata-Version: 2.1
Name: zwj-Pypi
Version: 0.1
Requires-Dist: numpy
Requires-Dist: pandas
